README.rst
setup.py
hasheroku/__init__.py
hasheroku/hasheroku.py
hasheroku.egg-info/PKG-INFO
hasheroku.egg-info/SOURCES.txt
hasheroku.egg-info/dependency_links.txt
hasheroku.egg-info/top_level.txt
hasheroku.egg-info/zip-safe
test/test_sampling.py