Metadata-Version: 1.2
Name: hasheroku
Version: 0.1.2
Summary: Generates nice heroku-ish hash from the string
Home-page: https://github.com/universome/hasheroku
Author: Ivan Skorokhodov
Author-email: iskorokhodov@gmail.com
License: BSD
Platform: UNKNOWN
Requires-Python: >=3
